diajax/__init__.py
diajax/audio.py
diajax/dia.py
diajax-0.1.7.dist-info/LICENSE
diajax-0.1.7.dist-info/METADATA
diajax-0.1.7.dist-info/WHEEL
diajax-0.1.7.dist-info/entry_points.txt
diajax-0.1.7.dist-info/top_level.txt
diajax-0.1.7.dist-info/RECORD
