Metadata-Version: 2.2
Name: diajax
Version: 0.1.7
Summary: Dia-JAX: A JAX port of Dia, the text-to-speech model for generating realistic dialogue from text with emotion and tone control
Home-page: https://github.com/jaco-bro/diajax
Author: J Joe
Author-email: backupjjoe@gmail.com
License: Apache-2.0
License-File: LICENSE
Requires-Dist: jax-metal==0.1.1; platform_system == "Darwin"
Requires-Dist: jaxlib==0.5.0; platform_system == "Darwin"
Requires-Dist: jax==0.5.0; platform_system == "Darwin"
Requires-Dist: flax==0.10.4
Requires-Dist: safetensors
Requires-Dist: pydantic
Requires-Dist: huggingface-hub
Requires-Dist: soundfile
Requires-Dist: descript-audio-codec
Requires-Dist: torchaudio
Provides-Extra: gpu
Requires-Dist: jax[cuda12]; extra == "gpu"
Provides-Extra: tpu
Requires-Dist: jax[tpu]; extra == "tpu"
Dynamic: author
Dynamic: author-email
Dynamic: description
Dynamic: description-content-type
Dynamic: home-page
Dynamic: license
Dynamic: provides-extra
Dynamic: requires-dist
Dynamic: summary
